custom_app_store/__init__.py
custom_app_store/custom_app_store.py
custom_app_store-0.1.0.dist-info/LICENSE
custom_app_store-0.1.0.dist-info/METADATA
custom_app_store-0.1.0.dist-info/WHEEL
custom_app_store-0.1.0.dist-info/top_level.txt
custom_app_store-0.1.0.dist-info/RECORD
